Workbook

Sheet Запрос Данных для расчета
B1: Запрос данных для расчета себестоимости СНК (прямые производственные расходы)
D2: Комментарий.
A3: 1. | B3: Наименование продукции | C3: ВМСН.713264.002 - Гайка
A4: 2. | B4: Количество едениц выпущенной продукции. Выпуск, шт. | C4: 1
A5: 3. | B5: Название цеха | C5: Участок производства изделий из пластмасс
A6: 4. | B6: Название станка | C6: Picaso Desinger X Series 2
A7: 4.1. | B7: Номинальная мощность станка по паспорту, кв*ч | C7: 0.7
A8: 4.2. | B8: Кол-во часов работы станка при вышеуказанном выпуске в строке 2) | C8: 1 ч 13 м
A9: 5. | B9: Материал/ Комплектующие | C9: ХХХХХХХХХХХХХ
A10: 5.1. | B10: Название сырья или материала | C10: АВS GF12 (Titan)
A11: 5.1.1. | B11: Ед.измерения материалов | C11: кг.
A12: 5.1.2. | B12: Расход сырья на 1 единицу изделия | C12: 0.019
A13: 5.2. | B13: Название сырья или материала (указывается, если используем более одного вида сырья)
A14: 5.2.1. | B14: Ед.измерения материалов
A15: 5.2.2. | B15: Расход сырья на 1 единицу изделия
A16: 5.3. | B16: Название сырья или материала (указывается, если используем более одного вида сырья)
A17: 5.3.1. | B17: Ед.измерения материалов
A18: 5.3.2. | B18: Расход сырья на 1 единицу изделия
A19: 5.4. | B19: Название сырья или материала
A20: 5.4.1. | B20: Ед.измерения материалов
A21: 5.4.2. | B21: Расход сырья на 1 единицу изделия
A22: 6. | B22: Трудозатраты | C22: ХХХХХХХХХХХХХ
A23: 6.1. | B23: Должность производственного рабочего | C23: Оператор оборудования трехмерной печати /Участок производства изделий из пластмасс /
A24: 6.1.1. | B24: Количество человек должности(указанной в пункте 6.1.) производят работу по выпуску (указанному в пункте 2.)изделий. | C24: 1
A25: 6.1.2. | B25: Количество часов на изготовление деталей всего выпуска одного вида изделия (количество деталей выпуска, указано в пункте 2.). Пример. Работало два человека, должность у которых одинаковая "Оператор лазерных установок 3 разряда /Участок механической обработки". Работали одновременно одну смену и вместе изготовили 100 штук деталей. Нужно указать в пункте 2. "100"; в пункте 6.1.1. "2 человека"; в пункте 6.1.2."11,00 часов". | C25: 1 ч 13 м
A26: 6.1.3. | B26: (Для мех.цеха, при производстве изделий комплектом на одной раскладке). Количество часов на партию изделий в одной раскладке. Если заполняется данная ячейка, предыдущая не заполняется. На все изделия при этом, используемые в раскладке, должны быть заполнены подобные таблицы)
A27: 6.2. | B27: Должность производственного рабочего, (указывается , если работы производятся более, чем одним человеком)
A28: 6.2.1. | B28: Количество человек должности(указанной в пункте 6.2.) производят работу по выпуску (указанному в пункте 2.)изделий.
A29: 6.2.2. | B29: Количество часов на изготовление деталей всего выпуска одного вида изделия (количество деталей выпуска, указано в пункте 2.).
A30: 6.2.3. | B30: (Для мех.цеха, при производстве изделий комплектом на одной раскладке). Количество часов на партию изделий в одной раскладке. Если заполняется данная ячейка, предыдущая не заполняется. На все изделия при этом, используемые в раскладке, должны быть заполнены подобные таблицы)
A31: 6.3. | B31: Должность производственного рабочего, (указывается , если работы производятся более, чем одним человеком)
A32: 6.3.1. | B32: Количество человек должности(указанной в пункте 6.3.) производят работу по выпуску (указанному в пункте 2.)изделий.
A33: 6.3.2. | B33: Количество часов на изготовление деталей всего выпуска одного вида изделия (количество деталей выпуска, указано в пункте 2.).
A34: 6.3.3. | B34: (Для мех.цеха, при производстве изделий комплектом на одной раскладке). Количество часов на партию изделий в одной раскладке. Если заполняется данная ячейка, предыдущая не заполняется. На все изделия при этом, используемые в раскладке, должны быть заполнены подобные таблицы)
A35: 7. | B35: Матрица/ Жертвенный стол | C35: ХХХХХХХХХХХХХ
A36: 7.1. | B36: Стоимость покупки мартрицы/ Стоимость жертвенного стола, руб.
A37: 7.1.1. | B37: Ресурс матрицы, шт
A38: 7.1.1. | B38: Ресурс матрицы/ жертвенного стола, часов
A39: 8. | B39: Упаковка | C39: ХХХХХХХХХХХХХ
A40: 8.1. | B40: Наименование номенклатуры упаковки.
A41: 8.1.1. | B41: Ед.измерения
A42: 8.1.2. | B42: Кол-во упаковки на 1 ед.продукции (Пример : В один пакет укладываем 1 изделие, то нужно указать 0,1 шт.; В один пакет укладываем 10 изделий, то нужно указать 0,1 шт.)
A43: 8.2. | B43: Наименование номенклатуры упаковки, указывается, если используется более одного вида упаковки.
A44: 8.2.1. | B44: Ед.измерения
A45: 8.2.2. | B45: Кол-во упаковки на 1 ед.продукции
A46: 8.3. | B46: Наименование номенклатуры упаковки, указывается, если используется более одного вида упаковки.
A47: 8.3.1. | B47: Ед.измерения
A48: 8.3.2. | B48: Кол-во упаковки на 1 ед.продукции

Sheet Оборудоание
A1: оборудование | B1: мощность
A2: Picaso Desinger X Series 2 | B2: 0.7
A3: Лазерный станок Wattsan 1610 LT | B3: 4
A4: Фрезерный станок Wattsan 1325 А1 | B4: 3.5
A5: 3-х осевой центр | B5: 8
A6: 5-ти осевой центр | B6: 15

Sheet Расчет
E1: Материалы, ч.т. | J1: Работы, в т.ч | O1: Матрица, в .т.ч. | R1: Амортизация, в т.ч. | V1: Электроэнергия, в т.ч. | Z1: Упаковка, в .ч.
A2: Наименование продукции | C2: Итого, на 1 ед, руб. | D2: Количество едениц выпущенной продукции. Выпуск, шт. | E2: Название сырья или материала | F2: Ед.измерения материалов | G2: Расход сырья на 1 единицу изделия | H2: Цена, руб без НДС | I2: Сырьевая с/с ед. руб. без НДС | J2: Должность производственного рабочего | K2: Количество человек производящих работу по выпуску всего объема изделий(см. п. 2.) | L2: Количество часов на изготовление деталей всего выпуска одного вида изделия | M2: Стоимость часа работы по ФОТ с учетом отчислений в фонды( Кф=1,317), (Кф рабочих часов в месяц = 1/165) | N2: Заработная плата на ед. изделия, руб. | O2: Стоимость покупки мартрицы, на 20 000 изделий | P2: Ресурс матрицы, шт | Q2: Стоимость матрицы на единицу, руб | R2: Наименование оборудования | S2: Количество часов работы станка/Оборудования | T2: Амортизация в час ( Кф=ОСост.ст./Мес.исп./242 часов в месяц | U2: Амотризация | V2: Мощность оборудования | W2: Кол-во часов использования | X2: Стоимость 1 Квт/Ч | Y2: Затраты на электроэнергию, руб | Z2: Наименование номенклатуры упаковки, указывается, если используется более одного вида упаковки. | AA2: Ед.измерения | AB2: Кол-во упаковки на 1 ед.продукции | AC2: Цена, руб без НДС | AD2: Упаковка, руб без НДС
A3: 1. | C3: 2. | D3: 2. | E3: 5.1. | F3: 5.1. | G3: 5.2. | J3: 6.1. | K3: 6.1.1. | L3: 6.1.2. | O3: 7.1. | P3: 7.1.1. | R3: 4. | S3: 4.2. | V3: 4.1. | W3: 4.2. | Z3: 8.1. | AA3: 8.1.1. | AB3: 8.1.2.
A4: =VLOOKUP(A$3,'Запрос Данных для расчета'!$A:$C,3,FALSE) -> ВМСН.713264.002 - Гайка | C4: =SUMIF($B$5:$B$100,"",C$5:C$100) -> #DIV/0! | D4: =VLOOKUP(D$3,'Запрос Данных для расчета'!$A:$C,3,FALSE) -> 1 | I4: =SUMIF($B$5:$B$100,"",I$5:I$100) -> 0 | N4: =SUMIF($B$5:$B$100,"",N$5:N$100) -> 733.96011 | Q4: =SUMIF($B$5:$B$100,"",Q$5:Q$100) -> #DIV/0! | U4: =SUMIF($B$5:$B$100,"",U$5:U$100) -> #N/A | Y4: =SUMIF($B$5:$B$100,"",Y$5:Y$100) -> 5.25 | AD4: =SUMIF($B$5:$B$100,"",AD$5:AD$100) -> 0
A5: Название сырья или материала | C5: =SUMIF(B:B,A5,C:C) -> 0 | D5: x | I5: =SUM(I6:I9) -> 0 | J5: x | K5: x | L5: x | M5: x | N5: x | O5: x | P5: x | Q5: x | R5: x | S5: x | U5: x | V5: x | W5: x | X5: x | Y5: x | Z5: x | AA5: x | AB5: x | AC5: x | AD5: x
A6: =E6 -> АВS GF12 (Titan) | B6: Название сырья или материала | C6: =I6 -> 0 | E6: =VLOOKUP(E$3,'Запрос Данных для расчета'!$A:$C,3,FALSE) -> АВS GF12 (Titan) | F6: =VLOOKUP(F$2,'Запрос Данных для расчета'!$B:$C,2,FALSE) -> кг. | G6: =VLOOKUP(G$2,'Запрос Данных для расчета'!$B:$C,2,FALSE) -> 0.019 | H6: =SUMIF('Справочник цен, ЗП '!$A:$A,E6,'Справочник цен, ЗП '!$C:$C) -> 0 | I6: =G6*H6 -> 0 | J6: х | K6: х | L6: х | M6: х | N6: х | V6: x | W6: x | X6: x | Y6: x | Z6: x | AA6: x | AB6: x | AC6: x | AD6: x
A7: =E7 -> 0 | B7: Название сырья или материала | C7: =I7 -> 0 | E7: =VLOOKUP("5.2.",'Запрос Данных для расчета'!$A:$C,3,FALSE) -> 0 | F7: =VLOOKUP("5.2.1.",'Запрос Данных для расчета'!$A:$C,3,FALSE) -> 0 | G7: =VLOOKUP("5.2.2.",'Запрос Данных для расчета'!$A:$C,3,FALSE) -> 0 | H7: =SUMIF('Справочник цен, ЗП '!A:A,E7,'Справочник цен, ЗП '!C:C) -> 0 | I7: =G7*H7 -> 0 | J7: х | K7: х | L7: х | M7: х | N7: х | O7: х | P7: х | Q7: х | R7: х | S7: х | U7: х | V7: х | W7: х | X7: х | Y7: х | Z7: х | AA7: х | AB7: х | AC7: х | AD7: х
A8: =E8 -> 0 | B8: Название сырья или материала | C8: =I8 -> 0 | E8: =VLOOKUP("5.3.",'Запрос Данных для расчета'!$A:$C,3,FALSE) -> 0 | F8: =VLOOKUP("5.3.1.",'Запрос Данных для расчета'!$A:$C,3,FALSE) -> 0 | G8: =VLOOKUP("5.3.2.",'Запрос Данных для расчета'!$A:$C,3,FALSE) -> 0 | H8: =SUMIF('Справочник цен, ЗП '!A:A,E8,'Справочник цен, ЗП '!C:C) -> 0 | I8: =G8*H8 -> 0 | J8: х | K8: х | L8: х | M8: х | N8: х | O8: х | P8: х | Q8: х | R8: х | S8: х | U8: х | V8: х | W8: х | X8: х | Y8: х | Z8: х | AA8: х | AB8: х | AC8: х | AD8: х
A9: =E9 -> 0 | B9: Название сырья или материала | C9: =I9 -> 0 | E9: =VLOOKUP("5.4.",'Запрос Данных для расчета'!$A:$C,3,FALSE) -> 0 | F9: =VLOOKUP("5.4.1.",'Запрос Данных для расчета'!$A:$C,3,FALSE) -> 0 | G9: =VLOOKUP("5.4.2.",'Запрос Данных для расчета'!$A:$C,3,FALSE) -> 0 | H9: =SUMIF('Справочник цен, ЗП '!A:A,E9,'Справочник цен, ЗП '!C:C) -> 0 | I9: =G9*H9 -> 0 | J9: х | K9: х | L9: х | M9: х | N9: х | O9: х | P9: х | Q9: х | R9: х | S9: х | U9: х | V9: х | W9: х | X9: х | Y9: х | Z9: х | AA9: х | AB9: х | AC9: х | AD9: х
A10: Заработная плата | C10: =SUMIF(B:B,A10,C:C) -> 733.96011 | D10: x | I10: x | N10: =SUM(N11:N13) -> 733.96011 | Q10: x | U10: x | Y10: x | AD10: x
A11: =J11 -> Оператор оборудования трехмерной печати /Участок производства изделий из пластмасс / | B11: Заработная плата | C11: =N11 -> 733.96011 | E11: х | F11: х | G11: х | H11: х | I11: х | J11: =VLOOKUP(J$3,'Запрос Данных для расчета'!$A:$C,3,FALSE) -> Оператор оборудования трехмерной печати /Участок производства изделий из пластмасс / | K11: =VLOOKUP(K$3,'Запрос Данных для расчета'!$A:$C,3,FALSE) -> 1 | L11: =VLOOKUP(L$3,'Запрос Данных для расчета'!$A:$C,3,FALSE) -> 1 ч 13 м | M11: =VLOOKUP(J11,'Справочник цен, ЗП '!H:K,4,FALSE) -> 733.96011 | N11: =PRODUCT(K11:M11)/$D$4 -> 733.96011 | O11: х | P11: х | Q11: х | R11: х | S11: х | U11: х | V11: х | W11: х | X11: х | Y11: х | Z11: х | AA11: х | AB11: х | AC11: х | AD11: х
A12: =J12 -> 0 | B12: Заработная плата | C12: =N12 -> 0 | E12: х | F12: х | G12: х | H12: х | I12: х | J12: =VLOOKUP("6.2.",'Запрос Данных для расчета'!$A:$C,3,FALSE) -> 0 | K12: =VLOOKUP("6.2.1.",'Запрос Данных для расчета'!$A:$C,3,FALSE) -> 0 | L12: =VLOOKUP("6.2.2.",'Запрос Данных для расчета'!$A:$C,3,FALSE) -> 0 | M12: =SUMIF('Справочник цен, ЗП '!H:H,Расчет!J12,'Справочник цен, ЗП '!K:K) -> 0 | N12: =PRODUCT(K12:M12)/$D$4 -> 0 | O12: х | P12: х | Q12: х | R12: х | S12: х | U12: х | V12: х | W12: х | X12: х | Y12: х | Z12: х | AA12: х | AB12: х | AC12: х | AD12: х
A13: =J13 -> 0 | B13: Заработная плата | C13: =N13 -> 0 | E13: х | F13: х | G13: х | H13: х | I13: х | J13: =VLOOKUP("6.3.",'Запрос Данных для расчета'!$A:$C,3,FALSE) -> 0 | K13: =VLOOKUP("6.3.1.",'Запрос Данных для расчета'!$A:$C,3,FALSE) -> 0 | L13: =VLOOKUP("6.3.2.",'Запрос Данных для расчета'!$A:$C,3,FALSE) -> 0 | M13: =SUMIF('Справочник цен, ЗП '!H:H,Расчет!J13,'Справочник цен, ЗП '!K:K) -> 0 | N13: =PRODUCT(K13:M13)/$D$4 -> 0 | O13: х | P13: х | Q13: х | R13: х | S13: х | U13: х | V13: х | W13: х | X13: х | Y13: х | Z13: х | AA13: х | AB13: х | AC13: х | AD13: х
A14: Прочие прямые производственные расходы | C14: =SUMIF(B:B,A14,C:C) -> #DIV/0! | D14: x | I14: x | N14: x | Q14: =Q15 -> #DIV/0! | U14: =U16 -> #N/A | Y14: =SUM(Y15:Y18) -> 5.25 | AD14: =SUM(AD15:AD18) -> 0
A15: Матрица/ Жертвенный стол | B15: Прочие прямые производственные расходы | C15: =Q15 -> #DIV/0! | E15: х | F15: х | G15: х | H15: х | I15: х | J15: х | K15: х | L15: х | M15: х | N15: х | O15: =VLOOKUP(O$3,'Запрос Данных для расчета'!$A:$C,3,FALSE) -> 0 | P15: =SUMIF('Запрос Данных для расчета'!A:A,Расчет!$P$3,'Запрос Данных для расчета'!C:C) -> 0 | Q15: =IF(P15=100,O15/P15*(S16/D4),O15/P15) -> #DIV/0! | S15: х | U15: х | V15: х | W15: х | X15: х | Y15: х | Z15: х | AA15: х | AB15: х | AC15: х | AD15: х
A16: Амортизация | B16: Прочие прямые производственные расходы | C16: =U16 -> #N/A | E16: х | F16: х | G16: х | H16: х | I16: х | J16: х | K16: х | L16: х | M16: х | N16: х | O16: х | P16: х | Q16: х | R16: =VLOOKUP(R$3,'Запрос Данных для расчета'!$A:$C,3,FALSE) -> Picaso Desinger X Series 2 | S16: =VLOOKUP(S$3,'Запрос Данных для расчета'!$A:$C,3,FALSE) -> 1 ч 13 м | T16: =VLOOKUP(Расчет!$R16,'Справочник цен, ЗП '!$N:$Q,4,FALSE) -> #N/A | U16: =PRODUCT(S16:T16)/D4 -> #N/A | V16: х | W16: х | X16: х | Y16: х | Z16: х | AA16: х | AB16: х | AC16: х | AD16: х
A17: Электроэнергия | B17: Прочие прямые производственные расходы | C17: =Y17 -> 5.25 | E17: х | F17: х | G17: х | H17: х | I17: х | J17: х | K17: х | L17: х | M17: х | N17: х | O17: х | P17: х | Q17: х | R17: х | S17: х | U17: х | V17: =VLOOKUP(V$3,'Запрос Данных для расчета'!$A:$C,3,FALSE) -> 0.7 | W17: =VLOOKUP(W$3,'Запрос Данных для расчета'!$A:$C,3,FALSE) -> 1 ч 13 м | X17: 7.5 | Y17: =PRODUCT(V17:X17)/$D$4 -> 5.25 | Z17: х | AA17: х | AB17: х | AC17: х | AD17: х
A18: Упаковка | B18: Прочие прямые производственные расходы | C18: =AD18 -> 0 | E18: х | F18: х | G18: х | H18: х | I18: х | J18: х | K18: х | L18: х | M18: х | N18: х | O18: х | P18: х | Q18: х | R18: х | S18: х | U18: х | V18: х | W18: х | X18: х | Y18: х | Z18: =VLOOKUP(Z$3,'Запрос Данных для расчета'!$A:$C,3,FALSE) -> 0 | AA18: =VLOOKUP(AA$3,'Запрос Данных для расчета'!$A:$C,3,FALSE) -> 0 | AB18: =VLOOKUP(AB$3,'Запрос Данных для расчета'!$A:$C,3,FALSE) -> 0 | AC18: =SUMIF('Справочник цен, ЗП '!$A:$A,Z18,'Справочник цен, ЗП '!$C:$C) -> 0 | AD18: =PRODUCT(AB18:AC18) -> 0
A19: Накладные расходы, 20% | C19: =($C$6+$C$10+$C$14)*10% -> #DIV/0! | D19: x | I19: x | N19: x | Q19: x | U19: x | Y19: x | AD19: x
A20: Рентабельность, 10% | C20: =($C$6+$C$10+$C$14+$C$19)*10% -> #DIV/0! | D20: х | I20: x | N20: x | Q20: x | U20: x | Y20: x | AD20: x
A21: Налог на прибыль | C21: =(C6+C10+C14+C19+C20)*2% -> #DIV/0! | D21: x | I21: x | N21: x | Q21: x | U21: x | Y21: x | AD21: x
A22: НДС | C22: =(C6+C10+C14+C19+C20+C21)*20% -> #DIV/0! | D22: x | I22: x | N22: x | Q22: x | U22: x | Y22: x | AD22: x

Sheet Справочник для Запроса
A1: Ед.измерения | B1: Подразделение | C1: Должности | D1: Ресурс матрицы | E1: Ресурс жертвенного стола
A2: шт. | B2: Участок производства изделий из пластмасс | C2: Обработчик изделий из пластмасс 2 разряда /Участок производства изделий из пластмасс / | D2: 20000 | E2: 100
A3: метр | B3: Участок механической обработки | C3: Оператор оборудования трехмерной печати /Участок производства изделий из пластмасс /
A4: м2 | B4: Участок сборочных линий БВС | C4: Машинист вакуум-формовочной машины 2 разряда /Участок производства изделий из пластмасс /
A5: кг. | B5: Участок композитного производства | C5: Литейщик пластмасс 2 разряда /Участок производства изделий из пластмасс /
A6: п.метр | C6: Литейщик пластмасс 2 разряда /Участок производства изделий из пластмасс /
C7: Мастер /Участок производства изделий из пластмасс /
C8: Наладчик инжекционно-литьевой машины /Участок производства изделий из пластмасс /
C9: Наладчик инжекционно-литьевой машины /Участок производства изделий из пластмасс /
C10: Начальник участка /Участок производства изделий из пластмасс /
C11: Инженер-технолог /Участок производства изделий из пластмасс /
C12: Слесарь-сборщик летательных аппаратов 3 разряда /Участок механической обработки /
C13: Оператор лазерных установок 3 разряда /Участок механической обработки /
C14: Слесарь-сборщик летательных аппаратов 4 разряда /Участок механической обработки /
C15: Оператор лазерных установок 3 разряда /Участок механической обработки /
C16: Оператор станков с программным управлением 3 разряда /Участок механической обработки /
C17: Оператор станков с программным управлением 4 разряда /Участок механической обработки /
C18: Начальник смены /Участок механической обработки /
... C53: Начальник участка /Участок композитного производства/

Sheet Справочник цен, ЗП 
A1: Номенклатура | B1: Документ | C1: Цена | H1: Должность | I1: ЗП | J1: ЗП+ФОНД Кф=1,317 | K1: Стоимость часа работы Кф=1/165 часов в месяц | N1: Станок | O1: Закупочная стоимость | P1: Амортизация 02 счет | Q1: за час
A2: Micro JST GH1.25 150mm 9Р Single Connector 28AWG | B2: Приходная накладная 270 (вх. 6) от 12.02.2024 | C2: 97.5 | H2: Обработчик изделий из пластмасс 2 разряда /Участок производства изделий из пластмасс / | I2: 68966 | J2: =I2*1.317 -> 90828.222 | K2: =J2/165 -> 550.47407 | L2: =COUNTIF($H$1:H1,H2) -> 0 | N2: Wattsan 1325A1 | O2: =1057960.01/1.2-145210 -> 736423.34 | P2: 10679.48 | Q2: =P2/(21*11) -> 46.231515
A3: Доставка товара клиенту | B3: Дополнительные расходы 577 (вх. 3359) от 07.05.2024 | C3: 408.33 | H3: Оператор оборудования трехмерной печати /Участок производства изделий из пластмасс / | I3: 91954 | J3: =I3*1.317 -> 121103.42 | K3: =J3/165 -> 733.96011 | L3: =COUNTIF($H$1:H2,H3) -> 0 | N3: 3D принтер Bambu lab X1 | P3: 5712.57 | Q3: =P3/(21*11) -> 24.72974
A4: кабель USB | B4: Приходная накладная 5206 (вх. 116) от 22.10.2024 | C4: 166.67 | H4: Машинист вакуум-формовочной машины 2 разряда /Участок производства изделий из пластмасс / | I4: 91954 | J4: =I4*1.317 -> 121103.42 | K4: =J4/165 -> 733.96011 | L4: =COUNTIF($H$1:H3,H4) -> 0 | N4: 3D принтер Designer X PRO series 2 (1) (инв.номер БП-000014) | P4: 18500 | Q4: =P4/(21*11) -> 80.08658
A5: Комплект разработчика радиоканала, Microhard pMDDL2350 | B5: Приходная накладная 4262 (вх. 65) от 01.03.2024 (удален) (не проведен) | C5: 209416.67 | H5: Литейщик пластмасс 2 разряда /Участок производства изделий из пластмасс / | I5: 103449 | J5: =I5*1.317 -> 136242.33 | K5: =J5/165 -> 825.71111 | L5: =COUNTIF($H$1:H4,H5) -> 0 | N5: 3D принтер Designer X PRO series 2 (2) (инв.номер БП-000013) | P5: 17760 | Q5: =P5/(21*11) -> 76.883117
A6: Разъемы питания АКБ male 10 pin | B6: Приходная накладная 1193 (вх. 119) от 14.05.2024 | C6: 51.67 | H6: Литейщик пластмасс 2 разряда /Участок производства изделий из пластмасс / | I6: 91954 | J6: =I6*1.317 -> 121103.42 | L6: =COUNTIF($H$1:H5,H6) -> 1 | N6: 3D принтер Designer X PRO series 2 (3) (инв.номер БП-000015) | P6: 17760 | Q6: =P6/(21*11) -> 76.883117
A7: !!!!!!!!Футболка т.-синяя L (48-50) | B7: Приходная накладная 4334 (вх. 146164) от 10.07.2024 | C7: 422.87 | H7: Мастер /Участок производства изделий из пластмасс / | I7: 126437 | J7: =I7*1.317 -> 166517.53 | K7: =J7/165 -> 1009.1971 | L7: =COUNTIF($H$1:H6,H7) -> 0 | N7: 3D принтер Designer X series 2 (1) (инв.номер БП-000020) | P7: 8760 | Q7: =P7/(21*11) -> 37.922078
A8: (ДЛАБ.563561.006) Аккумуляторная батарея Сибирь 34000mAh | B8: Приходная накладная 5223 (вх. 20241022-2) от 23.10.2024 | C8: 33333.33 | H8: Наладчик инжекционно-литьевой машины /Участок производства изделий из пластмасс / | I8: 137931 | J8: =I8*1.317 -> 181655.13 | K8: =J8/165 -> 1100.9402 | L8: =COUNTIF($H$1:H7,H8) -> 0 | N8: 3D принтер Designer XL series 2 (1) (инв.номер БП-000016) | P8: 23291.31 | Q8: =P8/(21*11) -> 100.82818
A9: [Компьютер] C825475Ц-AMD Ryzen 7 5700G / MicroStar A520M-A PRO / 16GB / SSD 512GB | B9: Приходная накладная 1837 (вх. 2407-9) от 24.07.2024 | C9: 27902.5 | H9: Начальник участка /Участок производства изделий из пластмасс / | I9: 195402 | J9: =I9*1.317 -> 257344.43 | K9: =J9/165 -> 1559.6632 | L9: =COUNTIF($H$1:H8,H9) -> 0 | N9: 3D принтер Designer XL series 2 (2) (инв.номер БП-000017) | P9: 23291.31 | Q9: =P9/(21*11) -> 100.82818
A10: [Ноутбук] C835390Ц-NUC / I70000 Платформа / 2x16GB / SSD 1Tb | B10: Приходная накладная 1213 (вх. 36467Ц) от 16.05.2024 | C10: 86138.05 | H10: Инженер-технолог /Участок производства изделий из пластмасс / | I10: 413794 | J10: =I10*1.317 -> 544966.7 | K10: =J10/165 -> 3302.8285 | L10: =COUNTIF($H$1:H9,H10) -> 0 | N10: 3D принтер Designer XL series 2 (3) (инв.номер БП-000018) | P10: 23291.31 | Q10: =P10/(21*11) -> 100.82818
A11: 0,4 - 0,8 мм, Набор сверел для печатных плат 10шт | B11: Приходная накладная 3960 (вх. 0788454) от 16.09.2024 | C11: 325 | H11: Слесарь-сборщик летательных аппаратов 3 разряда /Участок механической обработки / | I11: 80460 | J11: =I11*1.317 -> 105965.82 | K11: =J11/165 -> 642.21709 | L11: =COUNTIF($H$1:H10,H11) -> 0 | N11: 3D принтер Designer XL series 2 (4) (инв.номер БП-000019) | P11: 23291.31 | Q11: =P11/(21*11) -> 100.82818
A12: 0,8 - 1,2 мм, Набор сверел для печатных плат 10шт | B12: Приходная накладная 3960 (вх. 0788454) от 16.09.2024 | C12: 325 | H12: Слесарь-сборщик летательных аппаратов 4 разряда /Участок механической обработки / | I12: 103449 | J12: =I12*1.317 -> 136242.33 | K12: =J12/165 -> 825.71111 | L12: =COUNTIF($H$1:H11,H12) -> 0 | N12: 3D принтер Designer Х series 2 (2) (инв.номер БП-000021) | P12: 8760 | Q12: =P12/(21*11) -> 37.922078
A13: 0.056мкФ X7R 50В 10% 0805 | B13: Приходная накладная 3960 (вх. 0788454) от 16.09.2024 | C13: 5 | H13: Оператор лазерных установок 3 разряда /Участок механической обработки / | I13: 114942 | J13: =I13*1.317 -> 151378.61 | K13: =J13/165 -> 917.44615 | L13: =COUNTIF($H$1:H12,H13) -> 0 | N13: 3D принтер Designer Х series 2 (3) (инв.номер БП-000022) | P13: 8760 | Q13: =P13/(21*11) -> 37.922078
A14: 0.1Вт 0603 5.1 кОм, 5%, Чип резистор (SMD)\Тайвань | B14: Приходная накладная 251 (вх. 0096455) от 06.02.2024 | C14: 0.54 | H14: Оператор лазерных установок 3 разряда /Участок механической обработки / | I14: 91954 | J14: =I14*1.317 -> 121103.42 | L14: =COUNTIF($H$1:H13,H14) -> 1 | N14: 3D принтер Designer Х series 2 (4) (инв.номер БП-000023) | P14: 8760 | Q14: =P14/(21*11) -> 37.922078
A15: 0.25Вт 1206 220 Ом, 1%, Чип резистор (SMD)\Тайвань | B15: Приходная накладная 3841 (вх. 0763559) от 10.09.2024 | C15: 5.83 | H15: Оператор станков с программным управлением 3 разряда /Участок механической обработки / | I15: 114942 | J15: =I15*1.317 -> 151378.61 | K15: =J15/165 -> 917.44615 | L15: =COUNTIF($H$1:H14,H15) -> 0 | N15: 3D принтер Designer Х series 2 (5) (инв.номер БП-000027) | P15: 8760 | Q15: =P15/(21*11) -> 37.922078
A16: 0.25Вт 1206 (перемычка) 0 Ом, 1%, Чип резистор (SMD) | B16: Приходная накладная 3960 (вх. 0788454) от 16.09.2024 | C16: 5 | H16: Оператор станков с программным управлением 4 разряда /Участок механической обработки / | I16: 149425 | J16: =I16*1.317 -> 196792.73 | K16: =J16/165 -> 1192.6832 | L16: =COUNTIF($H$1:H15,H16) -> 0 | N16: 3D принтер Designer Х series 2 (6) (инв.номер БП-000028) | P16: 8760 | Q16: =P16/(21*11) -> 37.922078
A17: 0.25Вт 1206 1 кОм, 5%, Чип резистор (SMD)\Тайвань | B17: Приходная накладная 251 (вх. 0096455) от 06.02.2024 | C17: 5 | H17: Начальник смены /Участок механической обработки / | I17: 126437 | J17: =I17*1.317 -> 166517.53 | K17: =J17/165 -> 1009.1971 | L17: =COUNTIF($H$1:H16,H17) -> 0 | M17: 8 | N17: 3D принтер Designer Х series 2 (7) (инв.номер БП-000029) | P17: 8760 | Q17: =P17/(21*11) -> 37.922078
A18: 0.25Вт 1206 10 кОм, 5%, Чип резистор (SMD)\Тайвань | B18: Приходная накладная 251 (вх. 0096455) от 06.02.2024 | C18: 5 | H18: Начальник смены /Участок механической обработки / | I18: 114942 | J18: =I18*1.317 -> 151378.61 | L18: =COUNTIF($H$1:H17,H18) -> 1 | N18: 3D принтер Designer Х series 2 (8) (инв.номер БП-000030) | P18: 8760 | Q18: =P18/(21*11) -> 37.922078
A19: 0.25Вт 1206 100 кОм, 5%, Чип резистор (SMD)\Тайвань | B19: Приходная накладная 251 (вх. 0096455) от 06.02.2024 | C19: 5 | H19: Мастер /Участок механической обработки / | I19: 149425 | J19: =I19*1.317 -> 196792.73 | K19: =J19/165 -> 1192.6832 | L19: =COUNTIF($H$1:H18,H19) -> 0 | N19: 3D принтер PICASO 3D Designer XL S2 | P19: 27666.67 | Q19: =P19/(21*11) -> 119.76913
A20: 0.25Вт 1206 100 Ом, 1%, Чип резистор (SMD) | B20: Приходная накладная 3960 (вх. 0788454) от 16.09.2024 | C20: 5 | H20: Мастер /Участок механической обработки / | I20: 137931 | J20: =I20*1.317 -> 181655.13 | L20: =COUNTIF($H$1:H19,H20) -> 1 | N20: 3D сканер Shining FreeScan UE Pro | P20: 101351.35 | Q20: =P20/(21*11) -> 438.75043
A21: 0.25Вт 1206 100 Ом, 1%, Чип резистор (SMD)\Тайвань | B21: Приходная накладная 251 (вх. 0096455) от 06.02.2024 | C21: 5 | H21: Сервисный инженер /Ремонтно-механический отдел/ | I21: 149425 | J21: =I21*1.317 -> 196792.73 | K21: =J21/165 -> 1192.6832 | L21: =COUNTIF($H$1:H20,H21) -> 0 | N21: 3D щуп Digital | P21: 9803.14 | Q21: =P21/(21*11) -> 42.437835
A22: 0.25Вт 1206 18 Ом, 1%, Чип резистор (SMD) | B22: Приходная накладная 3960 (вх. 0788454) от 16.09.2024 | C22: 5 | H22: Начальник участка /Участок механической обработки/ | I22: 206897 | J22: =I22*1.317 -> 272483.35 | K22: =J22/165 -> 1651.4142 | L22: =COUNTIF($H$1:H21,H22) -> 0 | N22: Ethernet-коммутатор MES2424P, 24 порта 10/100/1000BASE-T (PoE/PoE+), 4 порта - 1 | P22: 5145.8 | Q22: =P22/(21*11) -> 22.27619
A23: 0.25Вт 1206 20 кОм, 5%, Чип резистор (SMD)\Тайвань | B23: Приходная накладная 251 (вх. 0096455) от 06.02.2024 | C23: 5 | H23: Главный механик /Ремонтно-механический отдел/ | I23: 206897 | J23: =I23*1.317 -> 272483.35 | K23: =J23/165 -> 1651.4142 | L23: =COUNTIF($H$1:H22,H23) -> 0 | N23: Ethernet-коммутатор MES2424P, 24 порта 10/100/1000BASE-T (PoE/PoE+), 4 порта - 2 | P23: 5145.8 | Q23: =P23/(21*11) -> 22.27619
A24: 0.25Вт 1206 4.7 кОм, 1%, Чип резистор (SMD) | B24: Приходная накладная 3960 (вх. 0788454) от 16.09.2024 | C24: 5 | H24: Монтажник электрооборудования летательных аппаратов 2 разряда /Участок сборочных линий БВС/ | I24: 80460 | J24: =I24*1.317 -> 105965.82 | K24: =J24/165 -> 642.21709 | L24: =COUNTIF($H$1:H23,H24) -> 0 | N24: Ethernet-коммутатор MES5332A, 1x10/100/1000BASE-T (ООВ), 32x10GBASE-R (SFP+)/1000BASE-X (SFP)-1 | P24: 22347.33 | Q24: =P24/(21*11) -> 96.741688
A25: 0.25Вт 1206 47 кОм, 5%, Чип резистор (SMD)\Тайвань | B25: Приходная накладная 251 (вх. 0096455) от 06.02.2024 | C25: 5 | H25: Монтажник электрооборудования летательных аппаратов 2 разряда /Участок сборочных линий БВС/ | I25: 68966 | J25: =I25*1.317 -> 90828.222 | L25: =COUNTIF($H$1:H24,H25) -> 1 | N25: Ethernet-коммутатор MES5332A, 1x10/100/1000BASE-T (ООВ), 32x10GBASE-R (SFP+)/1000BASE-X (SFP)-2 | P25: 22347.33 | Q25: =P25/(21*11) -> 96.741688
A26: 0.25Вт 1206 5.1 кОм, 5%, Чип резистор (SMD)\Тайвань | B26: Приходная накладная 251 (вх. 0096455) от 06.02.2024 | C26: 5 | H26: Слесарь-сборщик летательных аппаратов 3 разряда /Участок сборочных линий БВС/ | I26: 91954 | J26: =I26*1.317 -> 121103.42 | K26: =J26/165 -> 733.96011 | L26: =COUNTIF($H$1:H25,H26) -> 0 | N26: GRD Сварочный стол 24.12 К 10ХСНД ТУ 173510,001-2022(высота стола 750мм) 1 (инв.номер БП-000034) | P26: 18037.39 | Q26: =P26/(21*11) -> 78.083939
A27: 0.25Вт 1206(перемычка) 0 Ом 5%, Чип резистор (SMD) \Тайвань | B27: Приходная накладная 251 (вх. 0096455) от 06.02.2024 | C27: 5 | H27: Слесарь-сборщик летательных аппаратов 3 разряда /Участок сборочных линий БВС/ | I27: 80460 | J27: =I27*1.317 -> 105965.82 | L27: =COUNTIF($H$1:H26,H27) -> 1 | N27: GRD Сварочный стол 24.12 К 10ХСНД ТУ 173510,001-2022(высота стола 750мм) 2 (инв.номер БП-000035) | P27: 18037.39 | Q27: =P27/(21*11) -> 78.083939
A28: 0430300001@MOLEX | B28: Приходная накладная 2141 (вх. 824633) от 20.08.2024 | C28: 1.68 | H28: Монтажник электрооборудования летательных аппаратов 3 разряда /Участок сборочных линий БВС/ | I28: 91954 | J28: =I28*1.317 -> 121103.42 | K28: =J28/165 -> 733.96011 | L28: =COUNTIF($H$1:H27,H28) -> 0 | N28: M18 FMS305-121 Акк. торцовочная пила 1 | P28: 20106.25 | Q28: =P28/(21*11) -> 87.040043
A29: 0603WAF1003T5E | B29: Приходная накладная 942 (вх. 794660) от 11.04.2024 | C29: 11.92 | H29: Монтажник электрооборудования летательных аппаратов 3 разряда /Участок сборочных линий БВС/ | I29: 80460 | J29: =I29*1.317 -> 105965.82 | L29: =COUNTIF($H$1:H28,H29) -> 1 | N29: M18 FMS305-121 Акк. торцовочная пила 2 | P29: 20106.25 | Q29: =P29/(21*11) -> 87.040043
A30: 0603WAF200JT5E | B30: Приходная накладная 1041 (вх. 797647) от 19.04.2024 | C30: 5.7 | H30: Слесарь-сборщик летательных аппаратов 4 разряда /Участок сборочных линий БВС/ | I30: 103449 | J30: =I30*1.317 -> 136242.33 | K30: =J30/165 -> 825.71111 | L30: =COUNTIF($H$1:H29,H30) -> 0 | N30: QNAP TS-h973AX-32G NAS сервер сетевое хранилище | P30: 7869.32 | Q30: =P30/(21*11) -> 34.06632
A31: 0603WAF2400T5E | B31: Приходная накладная 1041 (вх. 797647) от 19.04.2024 | C31: 5.7 | H31: Слесарь-сборщик летательных аппаратов 4 разряда /Участок сборочных линий БВС/ | I31: 91954 | J31: =I31*1.317 -> 121103.42 | L31: =COUNTIF($H$1:H30,H31) -> 1 | N31: Автомобиль GREAT WALL POER VIN:LGWDAE196PJ646874 | P31: 101964.8 | Q31: =P31/(21*11) -> 441.40606
A32: 0603WAF2800T5E | B32: Приходная накладная 1041 (вх. 797647) от 19.04.2024 | C32: 5.72 | H32: Монтажник электрооборудования летательных аппаратов 4 разряда /Участок сборочных линий БВС/ | I32: 103449 | J32: =I32*1.317 -> 136242.33 | K32: =J32/165 -> 825.71111 | L32: =COUNTIF($H$1:H31,H32) -> 0 | N32: Автомобиль GREAT WALL POER VIN:LGWDAE199PJ651096 | P32: 101964.8 | Q32: =P32/(21*11) -> 441.40606
A33: 0603WAF4122T5E | B33: Приходная накладная 1041 (вх. 797647) от 19.04.2024 | C33: 5.7 | H33: Монтажник электрооборудования летательных аппаратов 5 разряда /Участок сборочных линий БВС/ | I33: 114942 | J33: =I33*1.317 -> 151378.61 | K33: =J33/165 -> 917.44615 | L33: =COUNTIF($H$1:H32,H33) -> 0 | N33: Автомобиль LADA 21214 VIN XTA21240R2501424 | P33: 23490.99 | Q33: =P33/(21*11) -> 101.6926
A34: 0603WAF5102T5E | B34: Приходная накладная 1041 (вх. 797647) от 19.04.2024 | C34: 5.7 | H34: Слесарь-сборщик летательных аппаратов 5 разряда /Участок сборочных линий БВС/ | I34: 114942 | J34: =I34*1.317 -> 151378.61 | K34: =J34/165 -> 917.44615 | L34: =COUNTIF($H$1:H33,H34) -> 0 | N34: АККУМУЛЯТОРНАЯ ПОГРУЖНАЯ ЦИРКУЛЯРНАЯ ПИЛА MILWAUKEE M18 FUEL FPS55-0P | P34: 2717.06 | Q34: =P34/(21*11) -> 11.762165
A35: 0603WAF510JT5E | B35: Приходная накладная 1041 (вх. 797647) от 19.04.2024 | C35: 5.72 | H35: Начальник смены /Участок сборочных линий БВС/ | I35: 126437 | J35: =I35*1.317 -> 166517.53 | K35: =J35/165 -> 1009.1971 | L35: =COUNTIF($H$1:H34,H35) -> 0 | N35: Аппарат аргонодуговой сварки Сварог "Инвертор сварочный TIG 315P AC/DC MULTIWAVE PRO E202 | P35: 6350.44 | Q35: =P35/(21*11) -> 27.491082
A36: 0603WAF7501T5E | B36: Приходная накладная 942 (вх. 794660) от 11.04.2024 | C36: 5.79 | H36: Мастер /Участок сборочных линий БВС/ | I36: 137931 | J36: =I36*1.317 -> 181655.13 | K36: =J36/165 -> 1100.9402 | L36: =COUNTIF($H$1:H35,H36) -> 0 | N36: Белмаш Станок круглопильный с подвижным столом TS-250-ST1300 S194A (инв.номер БП-000024) | P36: 9039.13 | Q36: =P36/(21*11) -> 39.130433
A37: 100пФ NPO 50В 5% 0805 | B37: Приходная накладная 3960 (вх. 0788454) от 16.09.2024 | C37: 10.83 | H37: Начальник участка /Участок сборочных линий БВС/ | I37: 206897 | J37: =I37*1.317 -> 272483.35 | K37: =J37/165 -> 1651.4142 | L37: =COUNTIF($H$1:H36,H37) -> 0 | N37: Вакуум формовочная машина VF2010 (инв.номер БП-000043) | P37: 8074.79 | Q37: =P37/(21*11) -> 34.955801
A38: 100пФ NPO 50В 5% 1206 | B38: Приходная накладная 3960 (вх. 0788454) от 16.09.2024 | C38: 10.83 | H38: Контуровщик стеклопластиковых изделий /Участок композитного производства/ | I38: 103449 | J38: =I38*1.317 -> 136242.33 | K38: =J38/165 -> 825.71111 | L38: =COUNTIF($H$1:H37,H38) -> 0 | N38: Вакуумная камера МT-V900-FR (инв.номер БП-000048) | P38: 12471.31 | Q38: =P38/(21*11) -> 53.988355
A39: 100СМ Сервоудлинитель с разъёмами (JR) и фиксатором 26AWG (1шт) | B39: Приходная накладная 197 (вх. 30) от 09.01.2024 | C39: 208.33 | H39: Контуровщик стеклопластиковых изделий /Участок композитного производства/ | I39: 80460 | J39: =I39*1.317 -> 105965.82 | L39: =COUNTIF($H$1:H38,H39) -> 1 | N39: Вауумный насос VSV-300 | P39: 11434.72 | Q39: =P39/(21*11) -> 49.500952
A40: 1054500101 | B40: Приходная накладная 943 (вх. 794659) от 11.04.2024 | C40: 172.95 | H40: Формовщик стеклопластиковых изделий /Участок композитного производства/ | I40: 103449 | J40: =I40*1.317 -> 136242.33 | K40: =J40/165 -> 825.71111 | L40: =COUNTIF($H$1:H39,H40) -> 0 | N40: Вертикально-фрезерный станок мод. МС955 (инв.номер БП-000049) | P40: 178903.48 | Q40: =P40/(21*11) -> 774.47394
A41: 10m Length ячменная бцмага для изоляции аккумулятора , 120 мм | B41: Авансовый отчет 183 от 18.04.2024 | C41: 2030.63 | H41: Формовщик стеклопластиковых изделий /Участок композитного производства/ | I41: 80460 | J41: =I41*1.317 -> 105965.82 | L41: =COUNTIF($H$1:H40,H41) -> 1 | N41: Вилочный электропогрузчик CHL CPD20SQ | P41: 29117.65 | Q41: =P41/(21*11) -> 126.05043
A42: 10-дюймовая вакуумная шина 22X10-10 | B42: Приходная накладная 3849 (вх. 102) от 10.09.2024 | C42: 7791.67 | H42: Формовщик стеклопластиковых изделий 3 разряда /Участок композитного производства/ | I42: 80460 | J42: =I42*1.317 -> 105965.82 | K42: =J42/165 -> 642.21709 | L42: =COUNTIF($H$1:H41,H42) -> 0 | N42: Волоконный лазерный маркер Zareff Fiber 20W | P42: 4122.95 | Q42: =P42/(21*11) -> 17.848268
A43: 10пФ NPO 50В 5% 0805 | B43: Приходная накладная 3960 (вх. 0788454) от 16.09.2024 | C43: 5.83 | H43: Слесарь по изготовлению и доводке деталей летательных аппаратов /Участок композитного производства/ | I43: 103449 | J43: =I43*1.317 -> 136242.33 | K43: =J43/165 -> 825.71111 | L43: =COUNTIF($H$1:H42,H43) -> 0 | N43: Галтовка CAF Vibro Plus | P43: 16361.59 | Q43: =P43/(21*11) -> 70.829394
A44: 1-1437565-6 | B44: Приходная накладная 356 (вх. 1676) от 15.02.2024 | C44: 8.05 | H44: Слесарь по изготовлению и доводке деталей летательных аппаратов /Участок композитного производства/ | I44: 80460 | J44: =I44*1.317 -> 105965.82 | L44: =COUNTIF($H$1:H43,H44) -> 1 | N44: Игровой ноутбук Hiper G16 16/1 IPS FHD i7-11700/32Gb/SSD 1Tb/RTX3070 8Gb | P44: 7983.91 | Q44: =P44/(21*11) -> 34.562381
A45: 12пФ NPO 50В 5% 0805 | B45: Приходная накладная 3960 (вх. 0788454) от 16.09.2024 | C45: 7.5 | H45: Сборщик изделий из стеклопластиков 3 разряда /Участок композитного производства/ | I45: 80460 | J45: =I45*1.317 -> 105965.82 | K45: =J45/165 -> 642.21709 | L45: =COUNTIF($H$1:H44,H45) -> 0 | N45: Инверторный сварочный полуавтомат Aurora PRO OVERMAN 200 Mosfet (1) | P45: 2924.35 | Q45: =P45/(21*11) -> 12.659524
A46: 15,6" Ноутбук Huawei MateBook D 15 (BoDE-WFH9)(FHD/IPS) i5 1155G7/16384/SSD 512/UMA/No OS/Space Grey | B46: Приходная накладная 799 (вх. ФЦ3-007693/8257) от 21.03.2024 | C46: 46665.83 | H46: Сборщик изделий из стеклопластиков 4 разряда /Участок композитного производства/ | I46: 103449 | J46: =I46*1.317 -> 136242.33 | K46: =J46/165 -> 825.71111 | L46: =COUNTIF($H$1:H45,H46) -> 0 | N46: Инверторный сварочный полуавтомат Aurora PRO OVERMAN 200 Mosfet (2) | P46: 2924.35 | Q46: =P46/(21*11) -> 12.659524
A47: 15.6" Ноутбук ASUS EXPERT BOOK (B1502CBA-BQ0421)(FHD/IPS)i3-1215U/8192/SSD 256/UMA/DOS/Star Black | B47: Приходная накладная 1431 (вх. Е-00101933/9517) от 14.05.2024 | C47: 35832.5 | H47: Раскройщик стекловолокнистых материалов /Участок композитного производства/ | I47: 103449 | J47: =I47*1.317 -> 136242.33 | K47: =J47/165 -> 825.71111 | L47: =COUNTIF($H$1:H46,H47) -> 0 | N47: Источник бесперебойного питания Hiden ИБП HIDEN EXPERT UDC92010H-RT, внешние акб - 1 | P47: 2206.77 | Q47: =P47/(21*11) -> 9.5531169
A48: 150пФ NPO 50В 5% 0805 | B48: Приходная накладная 3960 (вх. 0788454) от 16.09.2024 | C48: 10.83 | H48: Начальник смены /Участок композитного производства/ | I48: 126437 | J48: =I48*1.317 -> 166517.53 | K48: =J48/165 -> 1009.1971 | L48: =COUNTIF($H$1:H47,H48) -> 0 | N48: Источник бесперебойного питания Hiden ИБП HIDEN EXPERT UDC92010H-RT, внешние акб - 2 | P48: 2206.77 | Q48: =P48/(21*11) -> 9.5531169
A49: 15СМ Сервоудлинитель с разъёмами (JR) | B49: Приходная накладная 197 (вх. 30) от 09.01.2024 | C49: 191.67 | H49: Окрасчик изделий из стеклопластиков /Участок композитного производства/ | I49: 137931 | J49: =I49*1.317 -> 181655.13 | K49: =J49/165 -> 1100.9402 | L49: =COUNTIF($H$1:H48,H49) -> 0 | N49: Камера напыления обитаемая. Камера полимеризации проходного типа. Верхняя транспортная система (инв. | P49: 75066 | Q49: =P49/(21*11) -> 324.96104
A50: 17.3" Ноутбук MSI GF76 Кatana( B12VFK-271XRU)(FHD/IPS/144Hz)i7 12650H/16384/SSD 512/NV RTX4060/Black | B50: Приходная накладная 1431 (вх. Е-00101933/9517) от 14.05.2024 | C50: 105832.5 | H50: Мастер /Участок композитного производства/ | I50: 149425 | J50: =I50*1.317 -> 196792.73 | K50: =J50/165 -> 1192.6832 | L50: =COUNTIF($H$1:H49,H50) -> 0 | N50: Камера полимеризации Рэ=60кВт рабочий объем (ДхШхВ) 3500х2000х2000мм (инв. номер БП-000077) | P50: 77236.52 | Q50: =P50/(21*11) -> 334.35723
A51: 181555600 Дисплей Gaggi Titanium | B51: Приходная накладная 1048 (вх. 1777 - БЕЛ) от 22.04.2024 | C51: 3400 | H51: Мастер /Участок композитного производства/ | I51: 137931 | J51: =I51*1.317 -> 181655.13 | L51: =COUNTIF($H$1:H50,H51) -> 1 | N51: Камера тепла-холода-влаги EVCLIM-КТХВ-1000 K (ПНР, аттестация) | P51: 47540.98 | Q51: =P51/(21*11) -> 205.80511
A52: 18пФ NPO 50В 5% 0805 | B52: Приходная накладная 3960 (вх. 0788454) от 16.09.2024 | C52: 7.5 | H52: Начальник участка /Участок композитного производства/ | I52: 172414 | J52: =I52*1.317 -> 227069.24 | K52: =J52/165 -> 1376.1772 | L52: =COUNTIF($H$1:H51,H52) -> 0 | N52: Карманная метеостанция Kestrel 5700 Elite LiNK | P52: 1766.11 | Q52: =P52/(21*11) -> 7.6454978
A53: 1N4148WS | B53: Приходная накладная 353 (вх. 1672) от 15.02.2024 | C53: 2.54 | N53: Коммутатор MikroTik CRS326-24G-2S+RM 1 | P53: 8908.66 | Q53: =P53/(21*11) -> 38.565628
A54: 1N4148WS, Диод 100В 0.15А [SOD-323]\Hottech | B54: Приходная накладная 251 (вх. 0096455) от 06.02.2024 | C54: 0.67 | N54: Коммутатор MikroTik CRS326-24G-2S+RM 2 | P54: 8908.66 | Q54: =P54/(21*11) -> 38.565628
A55: 2006 5V PH2.0-2Pin Вентилятор центробежный 20x20x6 мм\СКБ Элемент | B55: Приходная накладная 4887 (вх. 0847353) от 03.10.2024 | C55: 850 | N55: Коммутатор MikroTik CRS326-24G-2S+RM 3 | P55: 8908.66 | Q55: =P55/(21*11) -> 38.565628
A56: 22пФ NPO 50В 5% 0805 | B56: Приходная накладная 3960 (вх. 0788454) от 16.09.2024 | C56: 7.5 | N56: Коммутатор MikroTik CRS326-24G-2S+RM 4 | P56: 8908.66 | Q56: =P56/(21*11) -> 38.565628
A57: 2400 Прямой ровинг ECR24-2400 | B57: Приходная накладная 2260 (вх. ПП-1891) от 29.08.2024 | C57: 199.3 | N57: Коммутатор MikroTik CRS326-24G-2S+RM 5 | P57: 8908.66 | Q57: =P57/(21*11) -> 38.565628
A58: 27" Монитор ARDOR GAMING AURORA AQ27H3 | B58: Приходная накладная 988 (вх. УТ-339) от 16.04.2024 | C58: 18750 | N58: Коммутатор MikroTik CRS326-24G-2S+RM 6 | P58: 8908.66 | Q58: =P58/(21*11) -> 38.565628
A59: 2CW and 2CCW Motor + 8331 Silver 4 pcs | B59: Авансовый отчет 261 от 19.01.2024 | C59: 2302.99 | N59: Коммутатор MikroTik CRS326-24G-2S+RM 7 | P59: 8908.66 | Q59: =P59/(21*11) -> 38.565628
A60: 2N7002, Транзистор N-MOSFET 60В 115мА [SOT-23-3]\UMW | B60: Приходная накладная 251 (вх. 0096455) от 06.02.2024 | C60: 2.5 | N60: Коммутатор MikroTik CRS326-24G-2S+RM 8 | P60: 8908.66 | Q60: =P60/(21*11) -> 38.565628
A61: 2N7002,215 | B61: Приходная накладная 369 (вх. 1670) от 15.02.2024 | C61: 4.55 | N61: Комплект мебели 1. Стол с опорной тумбой (1800х900х1800)2.Брифинг (1800х800h750) | P61: 2041.39 | Q61: =P61/(21*11) -> 8.8371861
A62: 2SK3018 | B62: Приходная накладная 1698 (вх. 0566549) от 12.07.2024 | C62: 5.83 | N62: Комплект разработчика радиоканала, Microhard pMDDL2350 | P62: 8376.67 | Q62: =P62/(21*11) -> 36.262641
A63: 2-местное распределительное подключение 90 642 1/2 | B63: Приходная накладная 5370 (вх. 283) от 30.10.2024 | C63: 3081.04 | N63: Компрессор DV-132-10 стационарный электрический винтовой (инв.номер БП-000052) | P63: 282529.57 | Q63: =P63/(21*11) -> 1223.0717
A64: 2х осевая камера U-30T | B64: Приходная накладная 1378 (вх. 220) от 07.06.2024 | C64: 512500 | N64: Компрессор Remeza ВК 20E-15-500Д 36509 | P64: 45719.42 | Q64: =P64/(21*11) -> 197.91957
... A164: AY-KA Колодка 3 гнезда, с заземлением, c крышкой каучуковая 5530000 | B164: Приходная накладная 1117 (вх. 4822349-МСК) от 02.05.2024 | C164: 302.5 | N164: Электродинамический вибрационный стенд | P164: 118073.77 | Q164: =P164/(21*11) -> 511.14186
A165: AY-KA Универсальный адаптер переходник 16А | B165: Приходная накладная 521 (вх. 2409755-МСК) от 06.03.2024 | C165: 64.2
A166: B5819WS-TP | B166: Приходная накладная 305 (вх. 1277) от 07.02.2024 | C166: 2.19
A167: B82498F3390J000 | B167: Приходная накладная 3960 (вх. 0788454) от 16.09.2024 | C167: 44.17
A168: BA-99C(Compact NS) 630/315A | B168: Приходная накладная 2226 (вх. 1521) от 27.08.2024 | C168: 47904.54
A169: Ballu Насос дренажный Machine DС Pump Pro проточный, 12 л/ч НС-1248311 | B169: Приходная накладная 1891 (вх. 8489957-МСК) от 29.07.2024 | C169: 3325.83
A170: Baofeng Рация UV-5R/3800мАч; | B170: Приходная накладная 327 (вх. 1723503-МСК) от 19.02.2024 | C170: 2023.33
A171: BARTEX Набор ключей трубчатый, 6 пр, , 6-17 мм, цинк, + 2 съемных рычага 170000 | B171: Приходная накладная 1891 (вх. 8489957-МСК) от 29.07.2024 | C171: 360.83
A172: BAT41KFILM диод ST | B172: Приходная накладная 4147 (вх. 1987) от 27.02.2024 | C172: 7.88
A173: BAT54C.215 | B173: Приходная накладная 353 (вх. 1672) от 15.02.2024 | C173: 1.6
A174: bbk Микроволновая печь 20MWS-711M/WS белый/серебро 00-00000605 | B174: Приходная накладная 89 (вх. 0329421-МСК) от 18.01.2024 | C174: 4500
A175: BC817-25,235 | B175: Приходная накладная 305 (вх. 1277) от 07.02.2024 | C175: 1.52
A176: BEFAST Дюбель распорный с шипами , синий цвет 6х30 1000 шт. K060301000BS | B176: Приходная накладная 1451 (вх. 6884893-МСК) от 17.06.2024 | C176: 312.5
... A3107: МДФ 280х2070х30мм (F) Кастамону | B3107: Приходная накладная 84 (вх. 53) от 14.01.2024 | C3107: 7691.67
A3108: МДФ шлифованная F 30х2800х2070мм | B3108: Приходная накладная 2306 (вх. УТ-883) от 03.09.2024 | C3108: 4440.72 | F3108: =C3108/100 -> 44.4072
A3109: Мебель для дома ET_Лоток для обуви (43x39x3,5) LT0301 черный | B3109: Приходная накладная 539 (вх. 35231095) от 12.03.2024 | C3109: 181.86
A3110: Мебель для общежитий MET_МДО Шкаф для одежды глубокий дуб сонома | B3110: Приходная накладная 4013 (вх. 39463686) от 18.09.2024 | C3110: 9167.5
A3111: Мегаомметр RGK RT-25 | B3111: Приходная накладная 407 (вх. 240222047) от 22.02.2024 | C3111: 12791.67
A3112: Мегаомметр Е6-31 | B3112: Приходная накладная 5186 (вх. 3486) от 21.10.2024 | C3112: 27805
A3113: МЕГЕОН Бинокулярная лупа 02815 | B3113: Приходная накладная 5090 (вх. 12221046-МСК) от 09.10.2024 | C3113: 1946.67
A3114: МЕГЕОН Вспомогательное устройство третья рука 02805 к0000006723 | B3114: Приходная накладная 1035 (вх. 4276926-БЛГ) от 16.04.2024 | C3114: 1888.33
A3115: МЕГЕОН Дымоуловитель со штативом и переходником под рукав 02813 к0000018206 | B3115: Приходная накладная 1609 (вх. 7530858-БЛГ) от 26.06.2024 | C3115: 6677.5
A3116: МЕГЕОН Жало медное 900M-T-0.8D-CU к0000033986 | B3116: Приходная накладная 3981 (вх. 10670269-БЛГ) от 17.09.2024 | C3116: 458.33
A3117: МЕГЕОН Жало медное 900M-T-2C-CU к0000033988 | B3117: Приходная накладная 3981 (вх. 10670269-БЛГ) от 17.09.2024 | C3117: 470
A3118: МЕГЕОН Жало медное 900M-T-3C-CU к0000033989 | B3118: Приходная накладная 1609 (вх. 7530858-БЛГ) от 26.06.2024 | C3118: 391.67
A3119: МЕГЕОН Источник питания | B3119: Приходная накладная 4275 (вх. 11702754-МСК) от 27.09.2024 | C3119: 11848.34
A3120: МЕГЕОН Комплект жал 900M-T-0.5C-K к0000036450 | B3120: Приходная накладная 2315 (вх. 10589721-МСК) от 04.09.2024 | C3120: 2355.83
... A5876: Ящик пластиковый Фин пак 400х300х280мм | B5876: Приходная накладная 5192 (вх. 4099) от 21.10.2024 | C5876: 319.17
A5877: Ящик полимерный многооборотный(250х150х130) | B5877: Приходная накладная 1966 (вх. 2944) от 02.08.2024 | C5877: 85 | H5877: 20% | I5877: 96 | J5877: 480
A5878: Ящик полимерный многооборотный(400х225х150) | B5878: Приходная накладная 1202 (вх. 11417/7) от 16.05.2024 | C5878: 314.33 | H5878: 20% | I5878: 123.4 | J5878: 617
A5879: Ящик универсальный 570x380x272 48Л | B5879: Приходная накладная 972 (вх. 4053429-МСК) от 15.04.2024 | C5879: 733.33 | H5879: 20% | I5879: 2300.8 | J5879: 11504
A5880: Катушка индуктивности SMD | B5880: Ввод начальных остатков №10 от 01.01.2024 | C5880: =J5877/F5880 -> 240 | D5880: =COUNTIF(A4:A5879,A5880) -> 0 | E5880: шт | F5880: 2 | G5880: 576 | H5880: 20% | I5880: 689.6 | J5880: 3448
A5881: Заклепка М3 100 шт Цилиндрическая для крепления камеры на крыло "Листопад" | B5881: Ввод начальных остатков №10 от 01.01.2024 | C5881: =J5878/F5881 -> 617 | D5881: =COUNTIF(A6:A5880,A5881) -> 0 | E5881: шт | F5881: 1 | G5881: 740.4 | H5881: 20% | I5881: 414.6 | J5881: 2073
A5882: Тяги передние регулируемые для Remo Hobby | B5882: Ввод начальных остатков №10 от 01.01.2024 | C5882: =J5879/F5882 -> 719 | D5882: =COUNTIF(A7:A5881,A5882) -> 0 | E5882: шт | F5882: 16 | G5882: 13804.8 | H5882: 20% | I5882: 458.4 | J5882: 2292
A5883: Радиоуправляемая рулевая тяга | B5883: Ввод начальных остатков №10 от 01.01.2024 | C5883: =J5880/F5883 -> 431 | D5883: =COUNTIF(A8:A5882,A5883) -> 0 | E5883: шт | F5883: 8 | G5883: 4137.6 | H5883: 20% | I5883: 1382.8 | J5883: 6914
A5884: Адаптер для монтажа на панель | B5884: Ввод начальных остатков №10 от 01.01.2024 | C5884: =J5881/F5884 -> 691 | D5884: =COUNTIF(A9:A5883,A5884) -> 0 | E5884: шт | F5884: 3 | G5884: 2487.6 | H5884: 20% | I5884: 516.8 | J5884: 2584
...
